catchup_schedules/__init__.py
catchup_schedules/main.py
catchup_schedules-1.0.2.dist-info/LICENSE
catchup_schedules-1.0.2.dist-info/METADATA
catchup_schedules-1.0.2.dist-info/WHEEL
catchup_schedules-1.0.2.dist-info/top_level.txt
catchup_schedules-1.0.2.dist-info/RECORD
