Metadata-Version: 2.1
Name: catchup-schedules
Version: 1.0.2
Summary: A robust scheduling module designed to catch up on periodic tasks that were skipped due to system pauses or downtime.
Home-page: https://github.com/1325ok/catchup-schedules
Author: 1325OK
Author-email: 1325ok.help@gmail.com
Project-URL: Source, https://github.com/1325ok/catchup-schedules
Keywords: schedules,remind,continue,date,task,save,scheduler,catchup,missed
Classifier: Programming Language :: Python :: 3
Classifier: License :: OSI Approved :: MIT License
Classifier: Operating System :: OS Independent
Requires-Python: >=3.6
License-File: LICENSE
